magneto/__init__.py
magneto/core.py
magneto/main.py
magneto/parser.py
magneto/ui.py
magneto/utils.py
magneto_cli-0.1.2.dist-info/METADATA
magneto_cli-0.1.2.dist-info/WHEEL
magneto_cli-0.1.2.dist-info/entry_points.txt
magneto_cli-0.1.2.dist-info/licenses/LICENSE
magneto_cli-0.1.2.dist-info/RECORD
