Metadata-Version: 2.4
Name: magneto-cli
Version: 0.1.2
Summary: Command-line tool for batch converting torrent files to magnet links
Project-URL: Homepage, https://github.com/mastaBriX/magneto
Project-URL: Repository, https://github.com/mastaBriX/magneto
Project-URL: Documentation, https://mastabrix.github.io/magneto/
Project-URL: Issues, https://github.com/mastaBriX/magneto/issues
Project-URL: Bug Reports, https://github.com/mastaBriX/magneto/issues
Project-URL: Source Code, https://github.com/mastaBriX/magneto
Author-email: Yuze Xie <xyzbrianx@gmail.com>
License: MIT License
License-File: LICENSE
Keywords: bittorrent,converter,magnet,torrent
Classifier: Development Status :: 4 - Beta
Classifier: Intended Audience :: End Users/Desktop
Classifier: License :: OSI Approved :: MIT License
Classifier: Programming Language :: Python :: 3
Classifier: Programming Language :: Python :: 3.7
Classifier: Programming Language :: Python :: 3.8
Classifier: Programming Language :: Python :: 3.9
Classifier: Programming Language :: Python :: 3.10
Classifier: Programming Language :: Python :: 3.11
Classifier: Programming Language :: Python :: 3.12
Classifier: Programming Language :: Python :: 3.13
Requires-Python: >=3.7
Requires-Dist: bencode-py>=4.0.0
Requires-Dist: colorama>=0.4.0
Provides-Extra: dev
Requires-Dist: black>=23.0.0; extra == 'dev'
Requires-Dist: pytest-cov>=4.0.0; extra == 'dev'
Requires-Dist: pytest>=7.0.0; extra == 'dev'
Requires-Dist: ruff>=0.1.0; extra == 'dev'
